artifacts_metadata/__init__.py
artifacts_metadata/artifacts_metadata_client.py
artifacts_metadata-0.0.5.dist-info/METADATA
artifacts_metadata-0.0.5.dist-info/WHEEL
artifacts_metadata-0.0.5.dist-info/top_level.txt
artifacts_metadata-0.0.5.dist-info/RECORD
