Metadata-Version: 2.1
Name: artifacts-metadata
Version: 0.0.5
Summary: A library for managing artifacts metadata in DynamoDB
Home-page: https://github.com/audienceproject/artifacts-metadata-py
Author: Cosmin Catalin Sanda
Author-email: cosmin@audienceproject.com
License: UNKNOWN
Platform: UNKNOWN
Requires-Python: >=3
Requires-Dist: boto3 (>=1.0.0)
